yafowil.widget.color-1.0a2-py3.9-nspkg.pth
yafowil/widget/color/__init__.py
yafowil/widget/color/example.py
yafowil/widget/color/tests.py
yafowil/widget/color/widget.py
yafowil/widget/color/locales/yafowil.widget.color.pot
yafowil/widget/color/locales/de/LC_MESSAGES/yafowil.widget.color.mo
yafowil/widget/color/locales/de/LC_MESSAGES/yafowil.widget.color.po
yafowil/widget/color/locales/en/LC_MESSAGES/yafowil.widget.color.mo
yafowil/widget/color/locales/en/LC_MESSAGES/yafowil.widget.color.po
yafowil/widget/color/resources/widget.css
yafowil/widget/color/resources/widget.js
yafowil/widget/color/resources/widget.min.js
yafowil/widget/color/resources/iro/iro.js
yafowil/widget/color/resources/iro/iro.min.js
yafowil.widget.color-1.0a2.dist-info/LICENSE.rst
yafowil.widget.color-1.0a2.dist-info/METADATA
yafowil.widget.color-1.0a2.dist-info/WHEEL
yafowil.widget.color-1.0a2.dist-info/entry_points.txt
yafowil.widget.color-1.0a2.dist-info/namespace_packages.txt
yafowil.widget.color-1.0a2.dist-info/top_level.txt
yafowil.widget.color-1.0a2.dist-info/RECORD
