Metadata-Version: 2.1
Name: yafowil.widget.color
Version: 1.0a2
Summary: Color picker widget for YAFOWIL
Home-page: http://github.com/conestack/yafowil.widget.color
Author: Yafowil Contributors
Author-email: dev@conestack.org
License: Simplified BSD
Classifier: License :: OSI Approved :: BSD License
Classifier: Environment :: Web Environment
Classifier: Operating System :: OS Independent
Classifier: Programming Language :: Python
Classifier: Topic :: Internet :: WWW/HTTP :: Dynamic Content
Classifier: Programming Language :: Python :: 2.7
Classifier: Programming Language :: Python :: 3.5
Classifier: Programming Language :: Python :: 3.6
Classifier: Programming Language :: Python :: 3.7
License-File: LICENSE.rst
Requires-Dist: setuptools
Requires-Dist: yafowil >2.2
Provides-Extra: test
Requires-Dist: lxml ; extra == 'test'
Requires-Dist: zope.testrunner ; extra == 'test'
